{
  "mqtt": [
    {
      "username": "vikramsphone",
      "password": "mqttdash123",
      "clientid": "mqttdash-ebd843fc"
    },
    {
      "username": "Linea",
      "password": "mg50028chars",
      "clientid": "Linea"
    }
  ],
  "socketio": [
    {
      "username": "OneHomeClient",
      "password": "OneHomeClient",
      "key": "AFGASDF292AAFDF"
    }
  ],
  "telgramBots": [
    {
      "token": "<not configured>",
      "mqttClients": [ "mqttdash-ebd843fc", "Nightfox_1000004" ],
      "socketIOClients": [ "ooruHomeClient" ]
    }
  ]
}